{"stats":{"minecraft:killed":{"minecraft:pillager":1},"minecraft:picked_up":{"minecraft:crafting_table":1,"minecraft:smoker":1,"minecraft:bucket":2,"minecraft:lava_bucket":1,"minecraft:blast_furnace":1,"minecraft:dirt":48,"minecraft:cobblestone":16,"minecraft:furnace":1},"minecraft:crafted":{"mojnovymod:cup":2,"mojnovymod:raw_cup":1,"minecraft:air":0},"minecraft:custom":{"minecraft:time_since_rest":3653,"minecraft:play_time":3653,"minecraft:interact_with_furnace":6,"minecraft:sprint_one_cm":184,"minecraft:damage_taken":50,"minecraft:walk_one_cm":3064,"minecraft:sneak_time":14,"minecraft:mob_kills":1,"minecraft:jump":4,"minecraft:interact_with_blast_furnace":3,"minecraft:leave_game":1,"minecraft:time_since_death":3653,"minecraft:total_world_time":25318,"minecraft:interact_with_smoker":2,"minecraft:interact_with_crafting_table":6,"minecraft:fall_one_cm":381,"minecraft:fly_one_cm":498}},"DataVersion":3218}